py_notepad/__init__.py
py_notepad/main.py
py_notepad/notepad_data_manager.py
py_notepad/py_notepad.py
py_notepad/py_notepad_widget.py
py_notepad/resources_rc.py
py_notepad/settings_dialog.py
heros_notepad-0.1.1.dist-info/METADATA
heros_notepad-0.1.1.dist-info/WHEEL
heros_notepad-0.1.1.dist-info/entry_points.txt
heros_notepad-0.1.1.dist-info/top_level.txt
heros_notepad-0.1.1.dist-info/RECORD
